dockertarpusher/__init__.py
dockertarpusher/command_line.py
dockertarpusher/dockertarpusher.py
dockertarpusher/manifestcreator.py
dockertarpush-0.17.dist-info/LICENSE
dockertarpush-0.17.dist-info/METADATA
dockertarpush-0.17.dist-info/WHEEL
dockertarpush-0.17.dist-info/entry_points.txt
dockertarpush-0.17.dist-info/top_level.txt
dockertarpush-0.17.dist-info/RECORD
