Metadata-Version: 2.1
Name: dockertarpush
Version: 0.17
Summary: Docker tar pusher to registry without docker daemon
Home-page: https://github.com/mathiasi/dockertarpusher
Author: Adam Raźniewski
Author-email: adam@razniewski.eu
License: UNKNOWN
Keywords: docker tar dockertar registry
Platform: UNKNOWN
Classifier: Programming Language :: Python :: 3
Classifier: License :: OSI Approved :: MIT License
Classifier: Operating System :: OS Independent
Requires-Dist: requests
